MANIFEST.in
README.md
setup.py
src/.DS_Store
src/sgs_utils/.DS_Store
src/sgs_utils/RGG_launcher.sh
src/sgs_utils/SGS_filter_launcher.sh
src/sgs_utils/Shogen_launcher.sh
src/sgs_utils/__init__.py
src/sgs_utils/add_gene_name.py
src/sgs_utils/add_gene_name.pyc
src/sgs_utils/add_gene_tag.py
src/sgs_utils/add_non_catalytic_links.py
src/sgs_utils/add_non_catalytic_links.pyc
src/sgs_utils/catalysis_extractor.sh
src/sgs_utils/correct_gene_mapping.py
src/sgs_utils/plop.pyc
src/sgs_utils/reaction_graph_generator.py
src/sgs_utils/sgs-utils.py
src/sgs_utils/sgs_add_reaction_sets.py
src/sgs_utils/sgs_add_reaction_sets.pyc
src/sgs_utils/sgs_domination.py
src/sgs_utils/sgs_domination.pyc
src/sgs_utils/sgs_filter.sh
src/sgs_utils/shogen2tab.py
src/sgs_utils/shogen2tab.pyc
src/sgs_utils/shogen_queries.py
src/sgs_utils/shogen_queries.pyc
src/sgs_utils/shogen_queries.sh
src/sgs_utils/sort_gene_list.sh
src/sgs_utils/two_columns_dict_extractor.sh
src/sgs_utils/utils.py
src/sgs_utils/utils.pyc
src/sgs_utils.egg-info/PKG-INFO
src/sgs_utils.egg-info/SOURCES.txt
src/sgs_utils.egg-info/dependency_links.txt
src/sgs_utils.egg-info/not-zip-safe
src/sgs_utils.egg-info/requires.txt
src/sgs_utils.egg-info/top_level.txt
src/sgs_utils/__pycache__/utils.cpython-35.pyc
src/sgs_utils/biocyc/.DS_Store
src/sgs_utils/biocyc/__init__.py
src/sgs_utils/biocyc/__init__.pyc
src/sgs_utils/biocyc/biocyc_chromosome_id_extractor.py
src/sgs_utils/biocyc/biocyc_chromosome_id_extractor.pyc
src/sgs_utils/biocyc/biocyc_genome_extractor.py
src/sgs_utils/biocyc/biocyc_genome_extractor.pyc
src/sgs_utils/biocyc/biocyc_parser.py
src/sgs_utils/biocyc/biocyc_parser.pyc
src/sgs_utils/biocyc/biocyc_reaction_extractor.py
src/sgs_utils/biocyc/biocyc_reaction_extractor.pyc
src/sgs_utils/gbk/__init__.py
src/sgs_utils/gbk/__init__.pyc
src/sgs_utils/gbk/gbk_genome_extractor.py
src/sgs_utils/gbk/gbk_genome_extractor.pyc
src/sgs_utils/libs/__init__.py
src/sgs_utils/libs/__init__.pyc
src/sgs_utils/libs/libs.py
src/sgs_utils/libs/tabfiles.py
src/sgs_utils/libs/tabfiles.pyc
src/sgs_utils/sbml/__init__.py
src/sgs_utils/sbml/__init__.pyc
src/sgs_utils/sbml/sbml_reaction_extractor.py
src/sgs_utils/sbml/sbml_reaction_extractor.pyc