Metadata-Version: 1.1
Name: sgs-utils
Version: 0.53
Summary: UNKNOWN
Home-page: https://github.com/pbordron/sgs-utils
Author: Philippe Bordron
Author-email: philippe.bordron+sgs@gmail.com
License: LGPL
Keywords: bioinformatics shogen SGS
Platform: UNKNOWN
Classifier: Development Status :: 4 - Beta
Classifier: License :: OSI Approved :: GNU Lesser General Public License v3 (LGPLv3)
Classifier: Programming Language :: PythonProgramming Language :: Python :: 2.7
Classifier: Topic :: Software Development :: Libraries :: Python Modules
Classifier: Operating System :: Unix
